[
    {
      "id": 1,
      "title": "Italy",
      "description": "Discover the beauty of italy",
      "imageUrl": "https://res.cloudinary.com/dlkcxiz0l/image/upload/f_auto,q_auto/v1/avatars/axh4wbrxnybhyfseiunc"
    },
    {
      "id": 2,
      "title": "Tokeyo",
      "description": "Discover the Beauty of Tokeyo",
      "imageUrl": "https://res.cloudinary.com/dlkcxiz0l/image/upload/f_auto,q_auto/itui3wow6vgn7mv7byue"
    },
    {
      "id": 3,
      "title": "Bali",
      "description": "Discover the Beauty of Bali",
      "imageUrl": "https://res.cloudinary.com/dlkcxiz0l/image/upload/f_auto,q_auto/v1/avatars/gfjli7deoq97ckzlaw8s"
    }
  ]
  